napari_tomodl/__init__.py
napari_tomodl/_reconstruction_widget.py
napari_tomodl/napari.yaml
napari_tomodl/widget_settings.py
napari_tomodl/_tests/__init__.py
napari_tomodl/processors/OPTProcessor.py
napari_tomodl/processors/__init__.py
napari_tomodl/processors/alternating.py
napari_tomodl/processors/functions_utils.py
napari_tomodl/processors/unet.py
napari_tomodl/processors/weights_tomodl100.ckpt
napari_tomodl-0.2.25.dist-info/LICENSE
napari_tomodl-0.2.25.dist-info/METADATA
napari_tomodl-0.2.25.dist-info/WHEEL
napari_tomodl-0.2.25.dist-info/entry_points.txt
napari_tomodl-0.2.25.dist-info/top_level.txt
napari_tomodl-0.2.25.dist-info/RECORD
