Metadata-Version: 2.1
Name: napari-tomodl
Version: 0.2.25
Summary: A plugin for optical projection tomography reconstruction with model-based neural networks.
Author: Marcos Antonio Obando, Minh Nhat Trinh, David Palecek, Germán Mato, Teresa Correia
Author-email: marcos.obando@ib.edu.ar
License: MIT
Classifier: Development Status :: 2 - Pre-Alpha
Classifier: Framework :: napari
Classifier: Intended Audience :: Developers
Classifier: License :: OSI Approved :: MIT License
Classifier: Operating System :: OS Independent
Classifier: Programming Language :: Python
Classifier: Programming Language :: Python :: 3
Classifier: Programming Language :: Python :: 3.9
Classifier: Programming Language :: Python :: 3.10
Classifier: Programming Language :: Python :: 3.11
Classifier: Topic :: Scientific/Engineering :: Image Processing
Requires-Python: >=3.10
License-File: LICENSE
Requires-Dist: magicgui
Requires-Dist: qtpy
Requires-Dist: scikit-image
Requires-Dist: scipy
Requires-Dist: qbi-radon
